Lab 3/src/Untitled/lockcomp.v
module lockcomp #(
    parameter size = 16,
    parameter password = 16'b0
) (
    input reset, preset,
    input [size-1:0] in,
    output reg equal
);

reg [size-1:0] stored_number = password;


always @(in or stored_number) begin
    if (in == stored_number) equal = 1;
    else equal = 0;
end

always @(posedge preset) stored_number = in;
always @(posedge reset) stored_number = password;    
endmodule

Lab 3/src/dlock.v
module dlock (
    input [3:0] SW16, // keyboard
    input SW1, //reset
    input SW2, //enter
    input SW3, //open check
    input rstn, //password reset
    input clk,
    output reg lock,
    output reg Error,
    output reg  [2:0] counter
);

reg comp_reset, comp_preset, locked;
wire equal;
reg [15:0] log;

reg [2:0] state, next;

parameter [2:0] 
DOOR_CLOSED = 3'b000, 
LOCK_UNLOCK = 3'b001, 
DOOR_OPEN = 3'b010, 
CHANGE_CODE = 3'b011, 
WRONG_CODE = 3'b100,
CHECK_PASSWORD = 3'b101;





lockcomp #(.password({4'b0011,4'b0011,4'b0011,4'b0011})) password_holder (
    .reset(comp_reset),
    .preset(comp_preset),
    .equal(equal),
    .in(log)
    );

always @(counter) if (counter>4) counter = 0;



always @(posedge clk or negedge rstn) begin

    if (!rstn) begin 
        state <= DOOR_OPEN;
        comp_reset <= 1;
        counter <= 0;
        locked <= 0;
    end

    else       state <= next;
end


always @(state, SW16, posedge SW1, posedge SW2, posedge SW3) begin
    next = state; lock = 0; Error = 0; comp_preset = 0; comp_reset = 0;

    case (state) 

    DOOR_CLOSED: begin
        
        if (SW2) begin
         log[counter*4 +:4] = SW16;
         counter = counter + 1;
        end    

        if (counter == 4) begin
            next = CHECK_PASSWORD;
        end    
    end

    CHECK_PASSWORD:begin
        if (equal == 1) next = LOCK_UNLOCK;
        else next = WRONG_CODE;
    end



    LOCK_UNLOCK: begin
        counter = 0;
        lock = 1;
        log = 16'bx;
        locked = ~locked;
        if(!SW3 && !locked) next = DOOR_CLOSED;
        else if (locked) next = DOOR_OPEN;
    end


    DOOR_OPEN: begin
        if(SW1 && !SW3) next = LOCK_UNLOCK;

        if(SW16 != 4'bz) begin
            log[counter*4 +:4] = SW16;
            counter = counter + 1;
        end

        if(log == 16'bxxxx111100011111) begin
            if(SW2) begin
            counter = 0;
            next = CHANGE_CODE;
            end
        end
    end


    CHANGE_CODE: begin

        if (SW2) begin
            if (
                SW16 == 4'b0001 ||  //*
                SW16 == 4'b0010 ||  //A
                SW16 == 4'b0110 ||  //B
                SW16 == 4'b0101 ||  //C
                SW16 == 4'b0100 ||  //D
                SW16 == 4'b1111 )   //#
                
                begin
                    next = WRONG_CODE;
                    counter = 0;
                end

                else begin 
                    log[counter*4 +:4] = SW16;
                    counter = counter + 1;

                    if (counter == 4) begin
                        comp_preset = 1;
                        next = DOOR_OPEN;
                    end
                end
        end  
    end



    WRONG_CODE: begin
        Error = 1;
        if(SW16 != 4'bz) begin
            log[counter*4 +:4] = SW16;
            counter = counter + 1;
        end

        if(log == 16'b0010011001100101) begin
            if(SW2) begin
            counter = 0;
            next = SW3?CHANGE_CODE:DOOR_CLOSED;
            end
        end
    end
    endcase
end





    
endmodule

Lab 3/src/dlock_tb.v
module dlock_tb;


reg [3:0] keyboard;
reg reset, open, enter, rstn, clk;

wire lock, Error;
wire [2:0] counter;


parameter [3:0]
in_1 = 4'b1101,
in_2 = 4'b1110,
in_3 = 4'b1000,
in_4 = 4'b0111,
in_5 = 4'b1010,
in_6 = 4'b000,
in_7 = 4'b1011,
in_8 = 4'b1001,
in_9 = 4'b0011,
in_A = 4'b0010,
in_B = 4'b0110,
in_C = 4'b0101,
in_D = 4'b0100,
in_star = 4'b0001,
in_hash = 4'b1111;


dlock dut(
    .SW16(keyboard),
    .SW1(reset),
    .SW2(enter),
    .SW3(open),
    .rstn(rstn),
    .clk(clk),
    .lock(lock),
    .Error(Error),
    .counter(counter)
);

always #5 clk=~clk;

initial begin
    $dumpfile("dlock.vcd");
    $dumpvars;

    clk = 0;
    open = 1;
    reset = 0;
    enter = 0;
    rstn = 1;
    #1 rstn = 0;
    #1 rstn = 1;


    //Checking if the door locks
    #10

    #5 reset = 1;
    #10 reset = 0;
    if (!dut.locked) $display("✅ Door refused to lock (door open).");
    else $display("❌ Door refused to lock (door open).");

    open = 0;

    #5 reset = 1;
    #10 reset = 0;
    if (dut.locked) $display("✅ Door Locked.");
    else $display("❌ Door Locked.");


    //Checking default password
    #1 keyboard = in_9;
    #15 enter = 1;
    #5 enter = 0;
    
    #15 enter = 1;
    #5 enter = 0;

    #15 enter = 1;
    #5 enter = 0;

    #15 enter = 1;
    #5 enter = 0;
    if (!dut.locked) $display("✅ Door Unlocked with default password.");
    else $display("❌ Door Unlocked with default password.");

    //Checking 



    #100

$finish;

    
end




endmodule

Lab 3/dlock.vcd
$date
	Wed Apr 26 19:45:21 2023
$end

$version
	Synopsys VCS version T-2022.06-SP1-1_Full64
$end

$timescale
	1ns
$end

$comment Csum: 1 902d8cecea617f86 $end


$scope module dlock_tb $end
$var reg 4 ! keyboard [3:0] $end
$var reg 1 " reset $end
$var reg 1 # open $end
$var reg 1 $ enter $end
$var reg 1 % rstn $end
$var reg 1 & clk $end
$var wire 1 ' lock $end
$var wire 1 ( Error $end
$var wire 3 ) counter [2:0] $end

$scope module dut $end
$var wire 4 * SW16 [3:0] $end
$var wire 1 + SW1 $end
$var wire 1 , SW2 $end
$var wire 1 - SW3 $end
$var wire 1 . rstn $end
$var wire 1 / clk $end
$var reg 1 0 lock $end
$var reg 1 1 Error $end
$var reg 3 2 counter [2:0] $end
$var reg 1 3 comp_reset $end
$var reg 1 4 comp_preset $end
$var reg 1 5 locked $end
$var wire 1 6 equal $end
$var reg 16 7 log [15:0] $end
$var reg 3 8 state [2:0] $end
$var reg 3 9 next [2:0] $end

$scope module password_holder $end
$var reg 16 : stored_number [15:0] $end
$var wire 1 ; reset $end
$var wire 1 < preset $end
$var wire 16 = in [15:0] $end
$var reg 1 > equal $end
$upscope $end

$upscope $end

$upscope $end

$enddefinitions $end

#0
$dumpvars
0(
0+
0,
1-
0&
04
03
01
00
0;
1.
0$
06
0'
x5
1#
0>
0<
0"
1%
bzzzz *
bxxx )
bxxx 2
bxxxxxxxxxxxxxxxx =
bzzzz !
bxxxxxxxxxxxxxxxx 7
bxxx 9
bxxx 8
b0011001100110011 :
0/
$end
#10
0%
0.
b010 8
13
1;
b000 2
b000 )
05
b010 9
03
0;
#20
1%
1.
#50
1&
1/
#100
0&
0/
#150
1&
1/
#170
1"
1+
#200
0&
0/
#250
1&
1/
#270
0"
0+
0#
0-
#300
0&
0/
#320
1"
1+
b001 9
#350
1&
1/
b001 8
b000 9
10
1'
15
#370
0"
0+
#400
0&
0/
#450
1&
1/
b000 8
00
0'
#500
0&
0/
#550
1&
1/
#600
0&
0/
#650
1&
1/
#700
0&
0/
#750
1&
1/
#770
b0011 !
b0011 *
#800
0&
0/
#820
1$
1,
bxxxxxxxxxxxx0011 7
bxxxxxxxxxxxx0011 =
b001 2
b001 )
#850
1&
1/
#870
0$
0,
#900
0&
0/
#950
1&
1/
#1000
0&
0/
#1020
1$
1,
bxxxxxxxx00110011 7
bxxxxxxxx00110011 =
b010 2
b010 )
#1050
1&
1/
#1070
0$
0,
#1100
0&
0/
#1150
1&
1/
#1200
0&
0/
#1220
1$
1,
bxxxx001100110011 7
bxxxx001100110011 =
b011 2
b011 )
#1250
1&
1/
#1270
0$
0,
#1300
0&
0/
#1350
1&
1/
#1400
0&
0/
#1420
1$
1,
b101 9
b0011001100110011 7
b0011001100110011 =
b100 2
b100 )
1>
16
#1450
1&
1/
b101 8
b001 9
b000 2
b000 )
#1470
0$
0,
#1480
bzzzz !
bzzzz *
#1500
0&
0/
#1550
1&
1/
b001 8
b010 9
10
1'
bxxxxxxxxxxxxxxxx 7
bxxxxxxxxxxxxxxxx =
05
0>
06
#1600
0&
0/
#1650
1&
1/
b010 8
00
0'
#1700
0&
0/
#1750
1&
1/
#1800
0&
0/
#1850
1&
1/
#1900
0&
0/
#1950
1&
1/
#2000
0&
0/
#2050
1&
1/
#2080
b1111 !
b1111 *
bxxxxxxxxxxxx1111 7
bxxxxxxxxxxxx1111 =
b001 2
b001 )
#2100
0&
0/
#2130
bzzzz !
bzzzz *
#2150
1&
1/
#2200
0&
0/
#2230
b0001 !
b0001 *
bxxxxxxxx00011111 7
bxxxxxxxx00011111 =
b010 2
b010 )
#2250
1&
1/
#2280
bzzzz !
bzzzz *
#2300
0&
0/
#2350
1&
1/
#2380
b1111 !
b1111 *
bxxxx111100011111 7
bxxxx111100011111 =
b011 2
b011 )
#2400
0&
0/
#2450
1&
1/
#2480
bzzzz !
bzzzz *
#2500
0&
0/
#2550
1&
1/
#2580
1$
1,
b011 9
b000 2
b000 )
#2600
0&
0/
#2630
0$
0,
#2650
1&
1/
b011 8
#2680
b1101 !
b1101 *
#2700
0&
0/
#2730
1$
1,
bxxxx111100011101 7
bxxxx111100011101 =
b001 2
b001 )
#2740
0$
0,
#2750
1&
1/
#2790
b1100 !
b1100 *
#2800
0&
0/
#2840
1$
1,
bxxxx111111001101 7
bxxxx111111001101 =
b010 2
b010 )
#2850
1&
1/
0$
0,
#2900
0&
0/
#2950
1&
1/
1$
1,
bxxxx110011001101 7
bxxxx110011001101 =
b011 2
b011 )
#2960
0$
0,
#3000
0&
0/
#3010
b0111 !
b0111 *
#3050
1&
1/
#3060
1$
1,
b010 9
14
1<
b0111110011001101 7
b0111110011001101 =
b100 2
b100 )
b0111110011001101 :
1>
16
#3070
0$
0,
#3100
0&
0/
#3120
bzzzz !
bzzzz *
#3150
1&
1/
b010 8
04
0<
#3200
0&
0/
#3250
1&
1/
#3300
0&
0/
#3350
1&
1/
#3400
0&
0/
#3450
1&
1/
#3500
0&
0/
#3550
1&
1/
#3600
0&
0/
#3620
1"
1+
b001 9
#3650
1&
1/
b001 8
b000 9
10
1'
bxxxxxxxxxxxxxxxx 7
bxxxxxxxxxxxxxxxx =
b000 2
b000 )
15
0>
06
#3670
0"
0+
#3700
0&
0/
#3750
1&
1/
b000 8
00
0'
#3800
0&
0/
#3820
b1010 !
b1010 *
#3850
1&
1/
#3870
1$
1,
bxxxxxxxxxxxx1010 7
bxxxxxxxxxxxx1010 =
b001 2
b001 )
#3880
0$
0,
#3900
0&
0/
#3930
b1011 !
b1011 *
#3950
1&
1/
#3980
1$
1,
bxxxxxxxx10111010 7
bxxxxxxxx10111010 =
b010 2
b010 )
#3990
0$
0,
#4000
0&
0/
#4040
b0011 !
b0011 *
#4050
1&
1/
#4090
1$
1,
bxxxx001110111010 7
bxxxx001110111010 =
b011 2
b011 )
#4100
0&
0/
0$
0,
#4150
1&
1/
b1101 !
b1101 *
#4200
0&
0/
1$
1,
b101 9
b1101001110111010 7
b1101001110111010 =
b100 2
b100 )
#4250
1&
1/
0$
0,
bzzzz !
bzzzz *
b101 8
b100 9
b000 2
b000 )
#4300
0&
0/
#4350
1&
1/
b100 8
11
1(
#4400
0&
0/
#4450
1&
1/
#4500
0&
0/
#4550
1&
1/
#4600
0&
0/
#4650
1&
1/
#4700
0&
0/
#4750
1&
1/
#4800
0&
0/
#4850
1&
1/
#4900
0&
0/
#4950
b0010 !
b0010 *
1&
1/
b1101001110110010 7
b1101001110110010 =
b001 2
b001 )
#5000
bzzzz !
bzzzz *
0&
0/
#5050
1&
1/
#5100
b0110 !
b0110 *
0&
0/
b1101001101100010 7
b1101001101100010 =
b010 2
b010 )
#5150
bzzzz !
bzzzz *
1&
1/
#5200
0&
0/
#5250
b0110 !
b0110 *
1&
1/
b1101011001100010 7
b1101011001100010 =
b011 2
b011 )
#5300
bzzzz !
bzzzz *
0&
0/
#5350
1&
1/
#5400
b0101 !
b0101 *
0&
0/
b000 9
b0101011001100010 7
b0101011001100010 =
b000 2
b000 )
#5450
1&
1/
b000 8
01
0(
#5500
0&
0/
#5550
1&
1/
#5600
0&
0/
#5650
1&
1/
#5700
0&
0/
#5750
1&
1/
#5800
0&
0/
#5850
1&
1/
#5900
0&
0/
#5950
b1101 !
b1101 *
1&
1/
#6000
1$
1,
0&
0/
b0101011001101101 7
b0101011001101101 =
b001 2
b001 )
#6010
0$
0,
#6050
1&
1/
#6060
b1100 !
b1100 *
#6100
0&
0/
#6110
1$
1,
b0101011011001101 7
b0101011011001101 =
b010 2
b010 )
#6120
0$
0,
#6150
1&
1/
#6200
0&
0/
#6220
1$
1,
b0101110011001101 7
b0101110011001101 =
b011 2
b011 )
#6230
0$
0,
#6250
1&
1/
#6280
b0111 !
b0111 *
#6300
0&
0/
#6330
1$
1,
b101 9
b0111110011001101 7
b0111110011001101 =
b100 2
b100 )
1>
16
#6350
1&
1/
b101 8
b001 9
b000 2
b000 )
#6380
0$
0,
#6390
bzzzz !
bzzzz *
#6400
0&
0/
#6450
1&
1/
b001 8
b010 9
10
1'
bxxxxxxxxxxxxxxxx 7
bxxxxxxxxxxxxxxxx =
05
0>
06
#6500
0&
0/
#6550
1&
1/
b010 8
00
0'
#6600
0&
0/
#6650
1&
1/
#6700
0&
0/
#6750
1&
1/
#6800
0&
0/
#6850
1&
1/
#6900
0&
0/
#6950
1&
1/
#6990
b1111 !
b1111 *
bxxxxxxxxxxxx1111 7
bxxxxxxxxxxxx1111 =
b001 2
b001 )
#7000
0&
0/
#7040
bzzzz !
bzzzz *
#7050
1&
1/
#7100
0&
0/
#7140
b0001 !
b0001 *
bxxxxxxxx00011111 7
bxxxxxxxx00011111 =
b010 2
b010 )
#7150
1&
1/
#7190
bzzzz !
bzzzz *
#7200
0&
0/
#7250
1&
1/
#7290
b1111 !
b1111 *
bxxxx111100011111 7
bxxxx111100011111 =
b011 2
b011 )
#7300
0&
0/
#7350
1&
1/
#7390
bzzzz !
bzzzz *
#7400
0&
0/
#7450
1&
1/
#7490
1$
1,
b011 9
b000 2
b000 )
#7500
0&
0/
#7540
0$
0,
#7550
1&
1/
b011 8
#7600
0&
0/
#7640
b0010 !
b0010 *
#7650
1&
1/
#7690
1$
1,
b100 9
#7700
0&
0/
#7740
0$
0,
#7750
1&
1/
b100 8
11
1(
bxxxx111100010010 7
bxxxx111100010010 =
b001 2
b001 )
#7800
0&
0/
#7850
1&
1/
#7900
0&
0/
#7950
1&
1/
#8000
0&
0/
#8050
1&
1/
#8100
0&
0/
#8150
1&
1/
#8200
0&
0/
#8250
1&
1/
#8300
0&
0/
#8350
1&
1/
#8390
bzzzz !
bzzzz *
#8400
0&
0/
#8450
1&
1/
#8490
b0110 !
b0110 *
bxxxx111101100010 7
bxxxx111101100010 =
b010 2
b010 )
#8500
0&
0/
#8540
bzzzz !
bzzzz *
#8550
1&
1/
#8600
0&
0/
#8640
b0110 !
b0110 *
bxxxx011001100010 7
bxxxx011001100010 =
b011 2
b011 )
#8650
1&
1/
#8690
bzzzz !
bzzzz *
#8700
0&
0/
#8750
1&
1/
#8790
b0101 !
b0101 *
b011 9
b0101011001100010 7
b0101011001100010 =
b000 2
b000 )
#8800
0&
0/
#8850
1&
1/
b011 8
01
0(
