Lab 3/src/Untitled/lockcomp.v
module lockcomp #(
    parameter size = 16,
    parameter password = 16'b0
) (
    input reset, preset,
    input [size-1:0] in,
    output reg equal
);

reg [size-1:0] stored_number = password;


always @(in or stored_number) begin
    if (in == stored_number) equal = 1;
    else equal = 0;
end

always @(posedge preset) stored_number = in;
always @(posedge reset) stored_number = password;    
endmodule

Lab 3/src/lockcomp_tb.v
module lockcomp_tb;

parameter password = 16'b0;
parameter size = 16;

reg reset, preset;
reg [size-1:0] input_number;
wire equal;



reg [size-1:0] temp;

lockcomp #(.password(password)) dut (.reset(reset), .preset(preset), .in(input_number), .equal(equal));


initial begin
    
    $dumpfile("lockcomp.vcd");
    $dumpvars;

    preset = 0;
    reset = 0;

    input_number = 0;
    #1
    if (equal==1) $display("✅ Default password working.");
    else $display("❌ Default password working.");

    #5
    temp = $random;
    input_number = temp;
    preset = 1;
    #1 
    preset = 0;
    if (dut.stored_number==temp) $display("✅ Preset Working. (Number Stored)");
    else $display("❌ Preset Working. (Number Stored)");
   
    #5
    input_number = $random;
    #1
    if (equal==0) $display("✅ Wrong comparison Working.");
    else $display("❌ Wrong comparison Working.");
    
    #5
    input_number = temp;
    #1
    if (equal==1) $display("✅ Preset Working. (Number Used)");
    else $display("❌ Preset Working. (Number Used)");
   
    reset=1;
    #1
    reset=0;
    #1
    input_number=16'b0;
    #1
    if (equal==1) $display("✅ Reset Working. (Correct Comparison)");
    else $display("❌ Reset Working.");
   
    #5
    input_number = $random;
    #10
    if (equal==0) $display("✅ Reset Working. (Wrong Comparison)");
    else $display("❌ Reset Working. (Wrong Comparison)");
    #10


    $finish;
end

    
endmodule

Lab 3/lockcomp.vcd
$date
	Wed Apr 26 19:47:17 2023
$end

$version
	Synopsys VCS version T-2022.06-SP1-1_Full64
$end

$timescale
	1ns
$end

$comment Csum: 1 bc31694948fd2e63 $end


$scope module lockcomp_tb $end
$var reg 1 ! reset $end
$var reg 1 " preset $end
$var reg 16 # input_number [15:0] $end
$var wire 1 $ equal $end
$var reg 16 % temp [15:0] $end

$scope module dut $end
$var reg 16 & stored_number [15:0] $end
$var wire 1 ' reset $end
$var wire 1 ( preset $end
$var wire 16 ) in [15:0] $end
$var reg 1 * equal $end
$upscope $end

$upscope $end

$enddefinitions $end

#0
$dumpvars
1*
0(
0'
1$
0"
0!
b0000000000000000 )
b0000000000000000 #
b0000000000000000 &
bxxxxxxxxxxxxxxxx %
$end
#60
b0011010100100100 %
b0011010100100100 #
b0011010100100100 )
1"
1(
0*
0$
b0011010100100100 &
1*
1$
#70
0"
0(
#120
b0101111010000001 #
b0101111010000001 )
0*
0$
#180
b0011010100100100 #
b0011010100100100 )
1*
1$
#190
1!
1'
b0000000000000000 &
0*
0$
#200
0!
0'
#210
b0000000000000000 #
b0000000000000000 )
1*
1$
#270
b1101011000001001 #
b1101011000001001 )
0*
0$
