Lab 3/src/vmcoffee.v
module vmcoffee (
    input C5, C10, NFC, BEANS, rstn, clk,
    input [4:0] WATER,
    output reg COFFEE, ERROR
);

parameter [1:0] IDLE = 2'b00, INSERTED5 = 2'b01, PAID = 2'b10, ERROR_FOUND = 2'b11;
reg [1:0] state, next;

always @(posedge clk or negedge rstn) begin
    if (!rstn) state <= IDLE;
    else       state <= next;
end

always @(state or C5 or C10 or NFC or BEANS or WATER) begin
    next = state; COFFEE = 0 ; ERROR = 1;
    case (state)
        IDLE: begin
            if (C5) next = INSERTED5;
            else if (C10) next = PAID;
            else if (!NFC) next = PAID;
            else if (WATER<2 || !BEANS) next = ERROR_FOUND;
        end

        INSERTED5: begin
            if (C5) next = PAID;
            else if (C10) next = PAID;
            else if (!NFC) next = PAID;
        end

        PAID: 
        begin
            next = IDLE;
            COFFEE = 1;
        end

        ERROR_FOUND: begin
            if (WATER>1 && BEANS) next=IDLE;
            ERROR = 0;
        end
    endcase
    
end



    
endmodule

Lab 3/src/vmcoffee_tb.v
module vmcoffee_tb;

reg C5, C10, NFC, BEANS, clk, rstn ;
wire ERROR, COFFEE;
reg [4:0] WATER ;

vmcoffee dut (.C5(C5), .C10(C10), .NFC(NFC), .BEANS(BEANS), .rstn(rstn), .clk(clk), .ERROR(ERROR), .COFFEE(COFFEE), .WATER(WATER)); 

always #5 clk = ~clk;

initial begin
    $dumpfile("vmcoffee.vcd");
    $dumpvars;

    WATER = 2;
    BEANS = 1;
    C5 = 0 ; 
    C10 = 0;
    NFC = 1;




    clk = 0;
    rstn = 0;
    #1 rstn = 1;
    if(dut.state==0) $display("✅ Reset Signal Working.");
    else $display("❌ Reset Signal Working.");

    #1 NFC = 0;
    #4 NFC = 1;
    
    if ( COFFEE == 1) $display("✅ NFC Payment Working.");
    else $display("❌ NFC Payment Working.");

    WATER = 1;

    #20 if(ERROR == 0) $display("✅ Water Sensor Working : No water.");
    else $display("❌ Water Sensor Working : No water.");

    #1 WATER = 30;

    #10 if(ERROR == 1) $display("✅ Water Sensor Working : Water Full.");
    else $display("❌ Water Sensor Working : Water Full.");

    #1 C5 = 1;
    #10 C5 = 0;

    #5 C5 = 1;
    #5 C5 = 0;

    #1 if(COFFEE == 1) $display("✅ Coin Payment Working.");
    else $display("❌ Coin Payment Working.");

    #10 BEANS = 0;

    #20 if(ERROR == 0) $display("✅ Bean Sensor Working : Out of beans.");
    else $display("❌ Bean Sensor Working : Out of beans.");

    #100 BEANS = 1;
    #10 if(ERROR == 1) $display("✅ Bean Sensor Working : Beans Full.");
    else $display("❌ Bean Sensor Working : Beans Full.");



    #150 $finish;
end



    
endmodule

Lab 3/Waveforms/vmcoffee.vcd
$date
	Wed Apr 26 19:47:12 2023
$end

$version
	Synopsys VCS version T-2022.06-SP1-1_Full64
$end

$timescale
	1ns
$end

$comment Csum: 1 9915fd256c336e3f $end


$scope module vmcoffee_tb $end
$var reg 1 ! C5 $end
$var reg 1 " C10 $end
$var reg 1 # NFC $end
$var reg 1 $ BEANS $end
$var reg 1 % clk $end
$var reg 1 & rstn $end
$var wire 1 ' ERROR $end
$var wire 1 ( COFFEE $end
$var reg 5 ) WATER [4:0] $end

$scope module dut $end
$var reg 2 * state [1:0] $end
$var wire 1 + C5 $end
$var wire 1 , C10 $end
$var wire 1 - NFC $end
$var wire 1 . BEANS $end
$var wire 1 / rstn $end
$var wire 1 0 clk $end
$var wire 5 1 WATER [4:0] $end
$var reg 1 2 COFFEE $end
$var reg 1 3 ERROR $end
$var reg 2 4 next [1:0] $end
$upscope $end

$upscope $end

$enddefinitions $end

#0
$dumpvars
1$
0"
0!
0(
1'
1#
0%
1.
0,
0+
02
13
1-
0/
0&
b00010 )
b00010 1
b00 4
b00 *
00
$end
#10
1&
1/
#20
0#
0-
b10 4
#50
1%
10
b10 *
b00 4
12
1(
#60
1#
1-
b00001 )
b00001 1
#100
0%
00
#150
1%
10
b00 *
b11 4
02
0(
#200
0%
00
#250
1%
10
b11 *
03
0'
#270
b11110 )
b11110 1
b00 4
#300
0%
00
#350
1%
10
b00 *
13
1'
#380
1!
1+
b01 4
#400
0%
00
#450
1%
10
b01 *
b10 4
#480
0!
0+
b01 4
#500
0%
00
#530
1!
1+
b10 4
#550
1%
10
b10 *
b00 4
12
1(
#580
0!
0+
#600
0%
00
#650
1%
10
b00 *
02
0(
#690
0$
0.
b11 4
#700
0%
00
#750
1%
10
b11 *
03
0'
#800
0%
00
#850
1%
10
#900
0%
00
#950
1%
10
#1000
0%
00
#1050
1%
10
#1100
0%
00
#1150
1%
10
#1200
0%
00
#1250
1%
10
#1300
0%
00
#1350
1%
10
#1400
0%
00
#1450
1%
10
#1500
0%
00
#1550
1%
10
#1600
0%
00
#1650
1%
10
#1700
0%
00
#1750
1%
10
#1800
0%
00
#1850
1%
10
#1890
1$
1.
b00 4
#1900
0%
00
#1950
1%
10
b00 *
13
1'
#1990
1!
1+
b01 4
#2000
0%
00
#2010
0!
0+
b00 4
#2020
1"
1,
b10 4
#2050
1%
10
b10 *
b00 4
12
1(
#2070
0"
0,
#2100
0%
00
#2150
1%
10
b00 *
02
0(
#2200
0%
00
#2220
1"
1,
b10 4
#2250
1%
10
b10 *
b00 4
12
1(
#2270
0"
0,
#2300
0%
00
#2350
1%
10
b00 *
02
0(
